prodigy_teams_recipes/__init__.py
prodigy_teams_recipes/about.json
prodigy_teams_recipes/about.py
prodigy_teams_recipes/recipes/__init__.py
prodigy_teams_recipes/recipes/audio.py
prodigy_teams_recipes/recipes/coref.py
prodigy_teams_recipes/recipes/curate.py
prodigy_teams_recipes/recipes/db_actions.py
prodigy_teams_recipes/recipes/dep.py
prodigy_teams_recipes/recipes/example_computations.py
prodigy_teams_recipes/recipes/image.py
prodigy_teams_recipes/recipes/llm.py
prodigy_teams_recipes/recipes/ner.py
prodigy_teams_recipes/recipes/pos.py
prodigy_teams_recipes/recipes/rel.py
prodigy_teams_recipes/recipes/review.py
prodigy_teams_recipes/recipes/secrets_example.py
prodigy_teams_recipes/recipes/sent.py
prodigy_teams_recipes/recipes/spans.py
prodigy_teams_recipes/recipes/terms.py
prodigy_teams_recipes/recipes/test_task.py
prodigy_teams_recipes/recipes/textcat.py
prodigy_teams_recipes/recipes/train.py
prodigy_teams_recipes/recipes/util.py
prodigy_teams_recipes/version/0.8.14_2023-04-07-13-53-57__1eb6cf61-27a2-4e08-b637-2c85139c8e08
prodigy_teams_recipes/version/0.8.14_2023-04-27-08-18-54_patch_dc7e0dd9-da84-472b-9289-c820c51463ab
prodigy_teams_recipes/version/0.8.15_2023-05-05-11-22-39_minor_ed2d179d-1199-47fd-b140-ea4cb80164a0
prodigy_teams_recipes/version/0.9.0_2023-05-09-09-37-09_patch_acd2c1a3-da73-4dee-afe5-17dc416db465
prodigy_teams_recipes/version/0.9.10_2023-10-31-20-17-56_patch_616a7344-37a9-494c-93ef-7f85b322b4de
prodigy_teams_recipes/version/0.9.10_2023-11-09-21-45-47_patch_c978de59-9bf2-4d56-9cb1-37c2b7d22284
prodigy_teams_recipes/version/0.9.11_2023-10-31-20-30-57_patch_99253db4-4295-4722-9dc0-c798ef1ea631
prodigy_teams_recipes/version/0.9.11_2023-11-10-04-06-46_patch_2ebeac55-35e1-4ce1-bea9-1853a2653bcf
prodigy_teams_recipes/version/0.9.12_2023-11-10-16-51-11_patch_fdf64993-90ea-48d6-9d2f-1706f454703c
prodigy_teams_recipes/version/0.9.13_2023-11-10-17-01-45_patch_98cddfb1-e4f5-4662-8df0-32e510088aa8
prodigy_teams_recipes-0.9.35.dist-info/LICENSE
prodigy_teams_recipes-0.9.35.dist-info/METADATA
prodigy_teams_recipes-0.9.35.dist-info/WHEEL
prodigy_teams_recipes-0.9.35.dist-info/entry_points.txt
prodigy_teams_recipes-0.9.35.dist-info/top_level.txt
prodigy_teams_recipes-0.9.35.dist-info/RECORD
