Metadata-Version: 2.1
Name: prodigy-teams-recipes
Version: 0.9.35
Summary: Recipes for Prodigy Teams
Home-page: https://prodi.gy
Author: ExplosionAI GmbH
Author-email: contact@explosion.ai
License: All rights reserved
License-File: LICENSE
Requires-Dist: confection>=0.1.0
Requires-Dist: plotext==4.2.0
Requires-Dist: prodigy>=1.16.0
Requires-Dist: prodigy-teams-recipes-sdk
Requires-Dist: psycopg2-binary
